pygmi/__init__.py
pygmi/main.py
pygmi/menu_default.py
pygmi/misc.py
pygmi/version.py
pygmi/bholes/__init__.py
pygmi/bholes/graphs.py
pygmi/bholes/iodefs.py
pygmi/bholes/menu.py
pygmi/clust/__init__.py
pygmi/clust/cluster.py
pygmi/clust/crisp_clust.py
pygmi/clust/fuzzy_clust.py
pygmi/clust/graphs.py
pygmi/clust/graphtool.py
pygmi/clust/menu.py
pygmi/clust/segmentation.py
pygmi/clust/super_class.py
pygmi/clust/var_ratio.py
pygmi/em/__init__.py
pygmi/em/menu.py
pygmi/em/tdem.py
pygmi/grav/__init__.py
pygmi/grav/dataprep.py
pygmi/grav/iodefs.py
pygmi/grav/menu.py
pygmi/helpdocs/html/bholes.cm.showlog.html
pygmi/helpdocs/html/bholes.dm.import.html
pygmi/helpdocs/html/bholes.html
pygmi/helpdocs/html/cluster.cm.exportclass.html
pygmi/helpdocs/html/cluster.cm.showbars.html
pygmi/helpdocs/html/cluster.cm.showclass.html
pygmi/helpdocs/html/cluster.cm.showgraphs.html
pygmi/helpdocs/html/cluster.cm.showmembership.html
pygmi/helpdocs/html/cluster.cm.stat.html
pygmi/helpdocs/html/cluster.dm.clust.html
pygmi/helpdocs/html/cluster.dm.crisp.html
pygmi/helpdocs/html/cluster.dm.fuzzy.html
pygmi/helpdocs/html/cluster.dm.scatter.html
pygmi/helpdocs/html/cluster.dm.seg.html
pygmi/helpdocs/html/cluster.dm.super.html
pygmi/helpdocs/html/cluster.html
pygmi/helpdocs/html/em.dm.tdem1dinv.html
pygmi/helpdocs/html/em.html
pygmi/helpdocs/html/faq.html
pygmi/helpdocs/html/faq.importxyz.html
pygmi/helpdocs/html/file.html
pygmi/helpdocs/html/genindex.html
pygmi/helpdocs/html/gravity.dm.import.html
pygmi/helpdocs/html/gravity.dm.process.html
pygmi/helpdocs/html/gravity.html
pygmi/helpdocs/html/index.html
pygmi/helpdocs/html/install.html
pygmi/helpdocs/html/interface.html
pygmi/helpdocs/html/mag.dm.igrf.html
pygmi/helpdocs/html/mag.dm.rtp.html
pygmi/helpdocs/html/mag.dm.tilt.html
pygmi/helpdocs/html/mag.dm.tiltdepth.html
pygmi/helpdocs/html/mag.html
pygmi/helpdocs/html/mt.cm.exportedi.html
pygmi/helpdocs/html/mt.cm.meta.html
pygmi/helpdocs/html/mt.cm.showgraphs.html
pygmi-3.2.9.7.dist-info/licenses/LICENSE.txt
pygmi-3.2.9.7.dist-info/METADATA
pygmi-3.2.9.7.dist-info/WHEEL
pygmi-3.2.9.7.dist-info/entry_points.txt
pygmi-3.2.9.7.dist-info/top_level.txt
pygmi-3.2.9.7.dist-info/RECORD
