Metadata-Version: 2.4
Name: pygmi
Version: 3.2.9.7
Summary: Python Geoscience Modelling and Interpretation
Author-email: Patrick Cole <pcole@geoscience.org.za>
Maintainer-email: Patrick Cole <pcole@geoscience.org.za>
License-Expression: GPL-3.0-or-later
Project-URL: homepage, http://patrick-cole.github.io/pygmi/
Project-URL: documentation, https://patrick-cole.github.io/pygmi/wiki.html
Project-URL: repository, https://github.com/Patrick-Cole/pygmi.git
Project-URL: changelog, https://github.com/Patrick-Cole/pygmi/blob/pygmi3/CHANGES.rst
Keywords: Geoscience,Geophysics,Magnetic,Gravity,Modelling,Interpretation,Remote Sensing
Classifier: Development Status :: 5 - Production/Stable
Classifier: Environment :: Win32 (MS Windows)
Classifier: Environment :: X11 Applications :: Qt
Classifier: Intended Audience :: Education
Classifier: Intended Audience :: End Users/Desktop
Classifier: Intended Audience :: Science/Research
Classifier: Natural Language :: English
Classifier: Operating System :: Microsoft :: Windows
Classifier: Operating System :: POSIX :: Linux
Classifier: Programming Language :: Python :: 3
Classifier: Topic :: Scientific/Engineering :: Mathematics
Classifier: Topic :: Scientific/Engineering :: Physics
Classifier: Topic :: Scientific/Engineering :: Image Processing
Classifier: Topic :: Scientific/Engineering :: Visualization
Classifier: Topic :: Software Development :: Libraries :: Python Modules
Requires-Python: >=3.10
License-File: LICENSE.txt
Requires-Dist: fiona>=1.10.1
Requires-Dist: geopandas>=1.0.1
Requires-Dist: h5netcdf>=1.6.1
Requires-Dist: matplotlib>=3.10.1
Requires-Dist: natsort>=8.4.0
Requires-Dist: numba>=0.61.2
Requires-Dist: numexpr>=2.10.2
Requires-Dist: openpyxl>=3.1.5
Requires-Dist: psutil>=7.0.0
Requires-Dist: pyside6>=6.9.0
Requires-Dist: pytest>=8.3.5
Requires-Dist: pyvista>=0.45.0
Requires-Dist: pyvistaqt>=0.11.2
Requires-Dist: rasterio>=1.4.3
Requires-Dist: rioxarray>=0.19.0
Requires-Dist: scikit-learn>=1.6.1
Requires-Dist: scikit-image>=0.25.2
Requires-Dist: shapelysmooth>=0.2.1
Requires-Dist: simpeg>=0.24.0
Requires-Dist: beautifulsoup4>=4.13.4
Requires-Dist: pyyaml>=6.0.2
Dynamic: license-file
